__init__.py
beta9/__init__.py
beta9/__main__.py
beta9/aio.py
beta9/channel.py
beta9/config.py
beta9/env.py
beta9/exceptions.py
beta9/integrations.py
beta9/logging.py
beta9/middleware.py
beta9/multipart.py
beta9/schema.py
beta9/sync.py
beta9/terminal.py
beta9/type.py
beta9/utils.py
beta9/abstractions/__init__.py
beta9/abstractions/endpoint.py
beta9/abstractions/function.py
beta9/abstractions/image.py
beta9/abstractions/map.py
beta9/abstractions/mixins.py
beta9/abstractions/output.py
beta9/abstractions/pod.py
beta9/abstractions/queue.py
beta9/abstractions/sandbox.py
beta9/abstractions/shell.py
beta9/abstractions/taskqueue.py
beta9/abstractions/volume.py
beta9/abstractions/base/__init__.py
beta9/abstractions/base/container.py
beta9/abstractions/base/runner.py
beta9/abstractions/experimental/__init__.py
beta9/abstractions/experimental/signal.py
beta9/abstractions/experimental/bot/__init__.py
beta9/abstractions/experimental/bot/bot.py
beta9/abstractions/experimental/bot/marker.py
beta9/abstractions/experimental/bot/types.py
beta9/abstractions/integrations/__init__.py
beta9/abstractions/integrations/fastmcp.py
beta9/abstractions/integrations/vllm.py
beta9/cli/__init__.py
beta9/cli/config.py
beta9/cli/container.py
beta9/cli/deployment.py
beta9/cli/dev.py
beta9/cli/extraclick.py
beta9/cli/machine.py
beta9/cli/main.py
beta9/cli/pool.py
beta9/cli/run.py
beta9/cli/secret.py
beta9/cli/serve.py
beta9/cli/shell.py
beta9/cli/task.py
beta9/cli/token.py
beta9/cli/volume.py
beta9/cli/worker.py
beta9/client/__init__.py
beta9/client/client.py
beta9/client/deployment.py
beta9/client/task.py
beta9/clients/__init__.py
beta9/clients/bot/__init__.py
beta9/clients/endpoint/__init__.py
beta9/clients/function/__init__.py
beta9/clients/gateway/__init__.py
beta9/clients/google/__init__.py
beta9/clients/google/api/__init__.py
beta9/clients/image/__init__.py
beta9/clients/map/__init__.py
beta9/clients/output/__init__.py
beta9/clients/pod/__init__.py
beta9/clients/secret/__init__.py
beta9-0.1.242.dist-info/METADATA
beta9-0.1.242.dist-info/WHEEL
beta9-0.1.242.dist-info/entry_points.txt
beta9-0.1.242.dist-info/top_level.txt
beta9-0.1.242.dist-info/RECORD
